rpgtoolkit/__init__.py
rpgtoolkit/dice.py
rpgtoolkit-0.0.1.dev1.dist-info/METADATA
rpgtoolkit-0.0.1.dev1.dist-info/WHEEL
rpgtoolkit-0.0.1.dev1.dist-info/RECORD
